{
  "entityType" : "WIDGET_TYPE",
  "entity" : {
    "fqn" : "wedo_entity_table",
    "name" : "WeDo Entity Table",
    "deprecated" : false,
    "image" : "tb-image;/api/images/system/device_admin_table_system_widget_image.png",
    "description" : "Customized entity table widget with preconfigured actions to create, update and delete devices.",
    "descriptor" : {
      "type" : "latest",
      "sizeX" : 7.5,
      "sizeY" : 6.5,
      "resources" : [ ],
      "templateHtml" : "<div class=\"sensor-container\">\r\n  <div class=\"metric-card\" [style.border-left-color]=\"borderColor\">\r\n    <tb-entities-table-widget [ctx]=\"ctx\"> </tb-entities-table-widget>\r\n  </div>\r\n</div>\r\n",
      "templateCss" : ":host {\r\n    display: block;\r\n    width: 100%;\r\n    height: 100%;\r\n    padding: 0;\r\n    margin: 0\r\n}\r\n\r\n.sensor-container {\r\n    font-family: 'Roboto', Arial, sans-serif;\r\n    background-color: #ffffff00;\r\n    width: 100%;\r\n    height: 100%;\r\n    box-sizing: border-box;\r\n    padding: 8px;\r\n}\r\n\r\n.metric-card {\r\n    background-color: #ffffff;\r\n    border-radius: 8px;\r\n    padding: 8px;\r\n    /* Reducido para dar más espacio interno */\r\n    display: flex;\r\n    flex-direction: column;\r\n    box-shadow: 0 4px 12px rgba(0, 0, 0, 0.12);\r\n    border-left: 4px solid #EE7623;\r\n    transition: all 0.2s ease;\r\n    height: 100%;\r\n    box-sizing: border-box;\r\n    overflow: hidden;\r\n    /* Crítico: cortar cualquier desbordamiento */\r\n}\r\n\r\n/* Contenedor de la tabla con dimensiones estrictas */\r\ntb-entities-table-widget {\r\n    width: 100%;\r\n    height: 100%;\r\n    display: block;\r\n    overflow: hidden;\r\n    position: relative;\r\n}\r\n\r\n/* Forzar contenedores internos */\r\n:host ::ng-deep tb-entities-table-widget>* {\r\n    max-width: 100% !important;\r\n}\r\n\r\n:host ::ng-deep .mat-toolbar {\r\n    background: transparent !important;\r\n    padding: 0 8px !important;\r\n    min-height: 40px !important;\r\n}\r\n\r\n:host ::ng-deep .mat-toolbar-row {\r\n    padding: 0 !important;\r\n    height: auto !important;\r\n    min-height: 40px !important;\r\n}\r\n\r\n:host ::ng-deep .tb-entity-table-content {\r\n    height: 100%;\r\n    display: flex;\r\n    flex-direction: column;\r\n    overflow: hidden;\r\n}\r\n\r\n/* Tabla principal con scroll interno */\r\n:host ::ng-deep .tb-entity-table {\r\n    width: 100%;\r\n    max-width: 100%;\r\n    overflow-x: auto;\r\n    overflow-y: auto;\r\n}\r\n\r\n/* Forzar que la tabla material respete el ancho */\r\n:host ::ng-deep .mat-table {\r\n    width: 100% !important;\r\n    max-width: 100% !important;\r\n    table-layout: fixed;\r\n    /* Importante: forzar tabla a respetar ancho del contenedor */\r\n}\r\n\r\n/* Filas y headers con ancho controlado */\r\n:host ::ng-deep mat-row,\r\n:host ::ng-deep mat-header-row {\r\n    width: 100% !important;\r\n    max-width: 100% !important;\r\n    box-sizing: border-box !important;\r\n}\r\n\r\n/* Celdas con padding interno */\r\n:host ::ng-deep mat-header-cell,\r\n:host ::ng-deep mat-cell {\r\n    padding: 0 12px !important;\r\n    box-sizing: border-box !important;\r\n    overflow: hidden;\r\n    text-overflow: ellipsis;\r\n}\r\n\r\n/* Primera columna con padding extra para separar del borde naranja */\r\n:host ::ng-deep mat-header-cell:first-of-type,\r\n:host ::ng-deep mat-cell:first-of-type {\r\n    padding-left: 16px !important;\r\n}",
      "controllerScript" : "self.onInit = function () {\r\n  var settings = self.ctx.settings;\r\n  self.ctx.$scope.borderColor = settings.borderColor || null;\r\n};\r\n\r\nself.onDataUpdated = function () {\r\n  self.ctx.$scope.entitiesTableWidget.onDataUpdated();\r\n};\r\n\r\nself.onEditModeChanged = function () {\r\n  self.ctx.$scope.entitiesTableWidget.onEditModeChanged();\r\n};\r\n\r\nself.typeParameters = function () {\r\n  return {\r\n    maxDatasources: 1,\r\n    hasDataPageLink: true,\r\n    warnOnPageDataOverflow: false,\r\n    dataKeysOptional: true,\r\n    supportsUnitConversion: true,\r\n  };\r\n};\r\n\r\nself.actionSources = function () {\r\n  return {\r\n    actionCellButton: {\r\n      name: \"widget-action.action-cell-button\",\r\n      multiple: true,\r\n      hasShowCondition: true,\r\n    },\r\n    rowClick: {\r\n      name: \"widget-action.row-click\",\r\n      multiple: false,\r\n    },\r\n    rowDoubleClick: {\r\n      name: \"widget-action.row-double-click\",\r\n      multiple: false,\r\n    },\r\n    cellClick: {\r\n      name: \"widget-action.cell-click\",\r\n      multiple: true,\r\n    },\r\n  };\r\n};\r\n\r\nself.onDestroy = function () {};\r\n",
      "settingsForm" : [ {
        "id" : "borderColor",
        "name" : "Color",
        "hint" : "Color borde izquierdo tabla",
        "group" : "Visual",
        "type" : "color",
        "default" : "#EE7623"
      } ],
      "settingsDirective" : "tb-entities-table-widget-settings",
      "dataKeySettingsDirective" : "tb-entities-table-key-settings",
      "hasBasicMode" : true,
      "basicModeDirective" : "tb-entities-table-basic-config",
      "defaultConfig" : "{\"showTitle\":true,\"backgroundColor\":\"rgb(255, 255, 255)\",\"color\":\"rgba(0, 0, 0, 0.87)\",\"padding\":\"4px\",\"settings\":{\"entitiesTitle\":\"Device admin table\",\"enableSearch\":true,\"enableSelectColumnDisplay\":true,\"enableStickyHeader\":true,\"enableStickyAction\":true,\"showCellActionsMenu\":true,\"reserveSpaceForHiddenAction\":\"true\",\"displayEntityName\":false,\"displayEntityLabel\":false,\"displayEntityType\":false,\"displayPagination\":true,\"defaultPageSize\":10,\"defaultSortOrder\":\"entityName\",\"useRowStyleFunction\":false},\"title\":\"WeDo Entity Table\",\"dropShadow\":true,\"enableFullscreen\":true,\"titleStyle\":{\"fontSize\":\"16px\",\"fontWeight\":400,\"padding\":\"5px 10px 5px 10px\"},\"showLegend\":false,\"datasources\":[{\"type\":\"function\",\"name\":\"Simulated\",\"dataKeys\":[{\"name\":\"f(x)\",\"type\":\"function\",\"label\":\"Entity name\",\"color\":\"#4caf50\",\"settings\":{},\"_hash\":0.8332260553092266,\"funcBody\":\"return 'Simulated';\",\"aggregationType\":null,\"units\":null,\"decimals\":null,\"usePostProcessing\":null,\"postFuncBody\":null},{\"name\":\"f(x)\",\"type\":\"function\",\"label\":\"Entity type\",\"color\":\"#f44336\",\"settings\":{},\"_hash\":0.08583217494773887,\"funcBody\":\"return 'Device';\",\"aggregationType\":null,\"units\":null,\"decimals\":null,\"usePostProcessing\":null,\"postFuncBody\":null},{\"name\":\"f(x)\",\"type\":\"function\",\"label\":\"Random\",\"color\":\"#f44336\",\"settings\":{\"columnWidth\":\"0px\",\"useCellStyleFunction\":false,\"cellStyleFunction\":\"\",\"useCellContentFunction\":false,\"cellContentFunction\":\"\"},\"_hash\":0.6401141393938932,\"funcBody\":\"var value = prevValue + Math.random() * 100 - 50;\\nvar multiplier = Math.pow(10, 2 || 0);\\nvar value = Math.round(value * multiplier) / multiplier;\\nif (value < -1000) {\\n\\tvalue = -1000;\\n} else if (value > 1000) {\\n\\tvalue = 1000;\\n}\\nreturn value;\"}],\"alarmFilterConfig\":{\"statusList\":[\"ACTIVE\"]}}],\"showTitleIcon\":false,\"titleIcon\":\"more_horiz\",\"iconColor\":\"rgba(0, 0, 0, 0.87)\",\"iconSize\":\"24px\",\"titleTooltip\":\"\",\"widgetStyle\":{},\"actions\":{\"headerButton\":[{\"name\":\"Add device\",\"icon\":\"add\",\"type\":\"customPretty\",\"customHtml\":\"<form #addDeviceForm=\\\"ngForm\\\" [formGroup]=\\\"addDeviceFormGroup\\\"\\n      (ngSubmit)=\\\"save()\\\" style=\\\"width: 480px;\\\">\\n  <mat-toolbar class=\\\"flex flex-row\\\" color=\\\"primary\\\">\\n    <h2>Add device</h2>\\n    <span class=\\\"flex-1\\\"></span>\\n    <button mat-icon-button\\n            (click)=\\\"cancel()\\\"\\n            type=\\\"button\\\">\\n      <mat-icon class=\\\"material-icons\\\">close</mat-icon>\\n    </button>\\n  </mat-toolbar>\\n  <mat-progress-bar color=\\\"warn\\\" mode=\\\"indeterminate\\\" *ngIf=\\\"isLoading$ | async\\\">\\n  </mat-progress-bar>\\n  <div style=\\\"height: 4px;\\\" *ngIf=\\\"!(isLoading$ | async)\\\"></div>\\n  <div mat-dialog-content>\\n    <div class=\\\"mat-padding flex flex-col\\\">\\n      <mat-form-field class=\\\"mat-block\\\">\\n        <mat-label>Device name</mat-label>\\n        <input matInput formControlName=\\\"deviceName\\\" required>\\n        <mat-error *ngIf=\\\"addDeviceFormGroup.get('deviceName').hasError('required')\\\">\\n          Device name is required.\\n        </mat-error>\\n      </mat-form-field>\\n      <div class=\\\"flex flex-row gap-2\\\">\\n        <tb-entity-subtype-autocomplete\\n            class=\\\"max-w-50% flex-full\\\"\\n            formControlName=\\\"deviceType\\\"\\n            [required]=\\\"true\\\"\\n            [entityType]=\\\"'DEVICE'\\\"\\n        ></tb-entity-subtype-autocomplete>\\n        <mat-form-field class=\\\"mat-block max-w-50% flex-full\\\">\\n          <mat-label>Label</mat-label>\\n          <input matInput formControlName=\\\"deviceLabel\\\">\\n        </mat-form-field>\\n      </div>\\n      <div formGroupName=\\\"attributes\\\" class=\\\"flex flex-row gap-2\\\">\\n        <mat-form-field class=\\\"mat-block max-w-50% flex-full\\\">\\n          <mat-label>Latitude</mat-label>\\n          <input type=\\\"number\\\" step=\\\"any\\\" matInput formControlName=\\\"latitude\\\">\\n        </mat-form-field>\\n        <mat-form-field class=\\\"mat-block max-w-50% flex-full\\\">\\n          <mat-label>Longitude</mat-label>\\n          <input type=\\\"number\\\" step=\\\"any\\\" matInput formControlName=\\\"longitude\\\">\\n        </mat-form-field>\\n      </div>\\n    </div>\\n  </div>\\n  <div mat-dialog-actions class=\\\"flex flex-row\\\">\\n    <span class=\\\"flex-1\\\"></span>\\n    <button mat-button color=\\\"primary\\\"\\n            type=\\\"button\\\"\\n            [disabled]=\\\"(isLoading$ | async)\\\"\\n            (click)=\\\"cancel()\\\" cdkFocusInitial>\\n      Cancel\\n    </button>\\n    <button mat-button mat-raised-button color=\\\"primary\\\"\\n            style=\\\"margin-right: 20px;\\\"\\n            type=\\\"submit\\\"\\n            [disabled]=\\\"(isLoading$ | async) || addDeviceForm.invalid || !addDeviceForm.dirty\\\">\\n      Create\\n    </button>\\n  </div>\\n</form>\\n\",\"customCss\":\"\",\"customFunction\":\"let $injector = widgetContext.$scope.$injector;\\nlet customDialog = $injector.get(widgetContext.servicesMap.get('customDialog'));\\nlet deviceService = $injector.get(widgetContext.servicesMap.get('deviceService'));\\nlet attributeService = $injector.get(widgetContext.servicesMap.get('attributeService'));\\n\\nopenAddDeviceDialog();\\n\\nfunction openAddDeviceDialog() {\\n    customDialog.customDialog(htmlTemplate, AddDeviceDialogController).subscribe();\\n}\\n\\nfunction AddDeviceDialogController(instance) {\\n    let vm = instance;\\n    \\n    vm.addDeviceFormGroup = vm.fb.group({\\n      deviceName: ['', [vm.validators.required]],\\n      deviceType: ['', [vm.validators.required]],\\n      deviceLabel: [''],\\n      attributes: vm.fb.group({\\n          latitude: [null],\\n          longitude: [null]\\n      })      \\n    });\\n    \\n    vm.cancel = function() {\\n        vm.dialogRef.close(null);\\n    };\\n    \\n    vm.save = function() {\\n        vm.addDeviceFormGroup.markAsPristine();\\n        let device = {\\n            name: vm.addDeviceFormGroup.get('deviceName').value,\\n            type: vm.addDeviceFormGroup.get('deviceType').value,\\n            label: vm.addDeviceFormGroup.get('deviceLabel').value\\n        };\\n        deviceService.saveDevice(device).subscribe(\\n            function (device) {\\n                saveAttributes(device.id).subscribe(\\n                    function () {\\n                        widgetContext.updateAliases();\\n                        vm.dialogRef.close(null);\\n                    }\\n                );\\n            }\\n        );\\n    };\\n    \\n    function saveAttributes(entityId) {\\n        let attributes = vm.addDeviceFormGroup.get('attributes').value;\\n        let attributesArray = [];\\n        for (let key in attributes) {\\n            attributesArray.push({key: key, value: attributes[key]});\\n        }\\n        if (attributesArray.length > 0) {\\n            return attributeService.saveEntityAttributes(entityId, \\\"SERVER_SCOPE\\\", attributesArray);\\n        } else {\\n            return widgetContext.rxjs.of([]);\\n        }\\n    }\\n}\",\"customResources\":[],\"id\":\"70837a9d-c3de-a9a7-03c5-dccd14998758\"}],\"actionCellButton\":[{\"name\":\"Edit device\",\"icon\":\"edit\",\"useShowWidgetActionFunction\":null,\"showWidgetActionFunction\":\"return true;\",\"type\":\"customPretty\",\"customHtml\":\"<form #editDeviceForm=\\\"ngForm\\\" [formGroup]=\\\"editDeviceFormGroup\\\"\\n      (ngSubmit)=\\\"save()\\\" style=\\\"width: 480px;\\\">\\n  <mat-toolbar class=\\\"flex flex-row\\\" color=\\\"primary\\\">\\n    <h2>Edit device</h2>\\n    <span class=\\\"flex-1\\\"></span>\\n    <button mat-icon-button\\n            (click)=\\\"cancel()\\\"\\n            type=\\\"button\\\">\\n      <mat-icon class=\\\"material-icons\\\">close</mat-icon>\\n    </button>\\n  </mat-toolbar>\\n  <mat-progress-bar color=\\\"warn\\\" mode=\\\"indeterminate\\\" *ngIf=\\\"isLoading$ | async\\\">\\n  </mat-progress-bar>\\n  <div style=\\\"height: 4px;\\\" *ngIf=\\\"!(isLoading$ | async)\\\"></div>\\n  <div mat-dialog-content>\\n    <div class=\\\"mat-padding flex flex-col\\\">\\n      <mat-form-field class=\\\"mat-block\\\">\\n        <mat-label>Device name</mat-label>\\n        <input matInput formControlName=\\\"deviceName\\\" required>\\n        <mat-error *ngIf=\\\"editDeviceFormGroup.get('deviceName').hasError('required')\\\">\\n          Device name is required.\\n        </mat-error>\\n      </mat-form-field>\\n      <div class=\\\"flex flex-row gap-2\\\">\\n        <tb-entity-subtype-autocomplete\\n            class=\\\"max-w-50% flex-full\\\"\\n            formControlName=\\\"deviceType\\\"\\n            [required]=\\\"true\\\"\\n            [entityType]=\\\"'DEVICE'\\\"\\n        ></tb-entity-subtype-autocomplete>\\n        <mat-form-field class=\\\"mat-block max-w-50% flex-full\\\">\\n          <mat-label>Label</mat-label>\\n          <input matInput formControlName=\\\"deviceLabel\\\">\\n        </mat-form-field>\\n      </div>\\n      <div formGroupName=\\\"attributes\\\" class=\\\"flex flex-row gap-2\\\">\\n        <mat-form-field class=\\\"mat-block max-w-50% flex-full\\\">\\n          <mat-label>Latitude</mat-label>\\n          <input type=\\\"number\\\" step=\\\"any\\\" matInput formControlName=\\\"latitude\\\">\\n        </mat-form-field>\\n        <mat-form-field class=\\\"mat-block max-w-50% flex-full\\\">\\n          <mat-label>Longitude</mat-label>\\n          <input type=\\\"number\\\" step=\\\"any\\\" matInput formControlName=\\\"longitude\\\">\\n        </mat-form-field>\\n      </div>\\n    </div>\\n  </div>\\n  <div mat-dialog-actions class=\\\"flex flex-row\\\">\\n    <span class=\\\"flex-1\\\"></span>\\n    <button mat-button color=\\\"primary\\\"\\n            type=\\\"button\\\"\\n            [disabled]=\\\"(isLoading$ | async)\\\"\\n            (click)=\\\"cancel()\\\" cdkFocusInitial>\\n      Cancel\\n    </button>\\n    <button mat-button mat-raised-button color=\\\"primary\\\"\\n            style=\\\"margin-right: 20px;\\\"\\n            type=\\\"submit\\\"\\n            [disabled]=\\\"(isLoading$ | async) || editDeviceForm.invalid || !editDeviceForm.dirty\\\">\\n      Update\\n    </button>\\n  </div>\\n</form>\\n\",\"customCss\":\"\",\"customFunction\":\"let $injector = widgetContext.$scope.$injector;\\nlet customDialog = $injector.get(widgetContext.servicesMap.get('customDialog'));\\nlet deviceService = $injector.get(widgetContext.servicesMap.get('deviceService'));\\nlet attributeService = $injector.get(widgetContext.servicesMap.get('attributeService'));\\n\\nopenEditDeviceDialog();\\n\\nfunction openEditDeviceDialog() {\\n    customDialog.customDialog(htmlTemplate, EditDeviceDialogController).subscribe();\\n}\\n\\nfunction EditDeviceDialogController(instance) {\\n    let vm = instance;\\n    \\n    vm.device = null;\\n    vm.attributes = {};\\n    \\n    vm.editDeviceFormGroup = vm.fb.group({\\n      deviceName: ['', [vm.validators.required]],\\n      deviceType: ['', [vm.validators.required]],\\n      deviceLabel: [''],\\n      attributes: vm.fb.group({\\n          latitude: [null],\\n          longitude: [null]\\n      })      \\n    });\\n    \\n    vm.cancel = function() {\\n        vm.dialogRef.close(null);\\n    };\\n    \\n    vm.save = function() {\\n        vm.editDeviceFormGroup.markAsPristine();\\n        if (vm.editDeviceFormGroup.get('deviceType').value !== vm.device.type) {\\n            delete vm.device.deviceProfileId;\\n        }\\n        vm.device.name = vm.editDeviceFormGroup.get('deviceName').value,\\n        vm.device.type = vm.editDeviceFormGroup.get('deviceType').value,\\n        vm.device.label = vm.editDeviceFormGroup.get('deviceLabel').value\\n        deviceService.saveDevice(vm.device).subscribe(\\n            function () {\\n                saveAttributes().subscribe(\\n                    function () {\\n                        widgetContext.updateAliases();\\n                        vm.dialogRef.close(null);\\n                    }\\n                );\\n            }\\n        );\\n    };\\n    \\n    getEntityInfo();\\n    \\n    function getEntityInfo() {\\n        deviceService.getDevice(entityId.id).subscribe(\\n            function (device) {\\n                attributeService.getEntityAttributes(entityId, 'SERVER_SCOPE',\\n                                                    ['latitude', 'longitude']).subscribe(\\n                   function (attributes) {\\n                        for (let i = 0; i < attributes.length; i++) {\\n                            vm.attributes[attributes[i].key] = attributes[i].value; \\n                        }\\n                        vm.device = device;\\n                        vm.editDeviceFormGroup.patchValue(\\n                            {\\n                                deviceName: vm.device.name,\\n                                deviceType: vm.device.type,\\n                                deviceLabel: vm.device.label,\\n                                attributes: {\\n                                    latitude: vm.attributes.latitude,\\n                                    longitude: vm.attributes.longitude\\n                                }\\n                            }, {emitEvent: false}\\n                        );\\n                   } \\n                );\\n            }\\n        );    \\n    }\\n    \\n    function saveAttributes() {\\n        let attributes = vm.editDeviceFormGroup.get('attributes').value;\\n        let attributesArray = [];\\n        for (let key in attributes) {\\n            attributesArray.push({key: key, value: attributes[key]});\\n        }\\n        if (attributesArray.length > 0) {\\n            return attributeService.saveEntityAttributes(entityId, 'SERVER_SCOPE', attributesArray);\\n        } else {\\n            return widgetContext.rxjs.of([]);\\n        }\\n    }\\n}\",\"customResources\":[],\"openInSeparateDialog\":false,\"openInPopover\":false,\"id\":\"93931e52-5d7c-903e-67aa-b9435df44ff4\"},{\"name\":\"Delete device\",\"icon\":\"delete\",\"type\":\"custom\",\"customFunction\":\"let $injector = widgetContext.$scope.$injector;\\nlet dialogs = $injector.get(widgetContext.servicesMap.get('dialogs'));\\nlet deviceService = $injector.get(widgetContext.servicesMap.get('deviceService'));\\n\\nopenDeleteDeviceDialog();\\n\\nfunction openDeleteDeviceDialog() {\\n    let title = \\\"Are you sure you want to delete the device \\\" + entityName +  \\\"?\\\";\\n    let content = \\\"Be careful, after the confirmation, the device and all related data will become unrecoverable!\\\";\\n    dialogs.confirm(title, content, 'Cancel', 'Delete').subscribe(\\n        function (result) {\\n            if (result) {\\n                deleteDevice();\\n            }\\n        }\\n    );\\n}\\n\\nfunction deleteDevice() {\\n    deviceService.deleteDevice(entityId.id).subscribe(\\n        function () {\\n            widgetContext.updateAliases();\\n        }\\n    );\\n}\\n\",\"id\":\"ec2708f6-9ff0-186b-e4fc-7635ebfa3074\"}]},\"configMode\":\"basic\"}"
    },
    "externalId" : null,
    "resources" : null,
    "id" : {
      "entityType" : "WIDGET_TYPE",
      "id" : "3b1f9341-4d55-11f1-96dd-cf2d8d8f620e"
    },
    "scada" : false,
    "tags" : [ "provisioning", "management", "administration", "admin" ]
  },
  "relations" : [ ],
  "attributes" : {
    "SERVER_SCOPE" : [ ]
  }
}